{
  "loading": "Cargando",
  "error": "Error",
  "welcom_to_paradise": "BIENVENIDO AL PARAÍSO",
  "i_agrre_to_the": "Estoy de acuerdo con la",
  "privacy_policy": "Política de Privacidad",
  "next": "Siguiente",
  "welcome_to_our_app": "¡Bienvenido a nuestra aplicación!",
  "discover_existinf_rewards": "Descubre recompensas emocionantes, bonos exclusivos y una experiencia de juego increíble. ¡Empecemos!",
  "point_1": "Punto-1",
  "point_2": "Punto-2",
  "point_3": "Punto-3",
  "point_we_provide_user_to_link": "Proporcionamos enlaces para que los usuarios reciban recompensas del juego Coin Master.",
  "provided_by_game_publisher": "Estos enlaces son proporcionados por el editor del juego Coin Master - Moon Active para dar giros y monedas a los jugadores.",
  "we_aggregate_those": "Agregamos estos enlaces para evitar que los jugadores pierdan tiempo buscando y se confundan con enlaces repetidos.",
  "step": "Paso",
  "game_installed": "Juego Coin Master instalado.",
  "complate_the_first_village": "Completa el tutorial del juego. Es mejor completar la primera aldea.",
  "to_receved_rewards_links": "Para recibir la recompensa del enlace, debes cumplir con los dos requisitos anteriores:",
  "daily_free_spin": "Giro Gratis Diario",
  "cm_guide": "Guía CM",
  "tips_and_tricks": "Consejos y Trucos",
  "privacy_and_policy": "Política de Privacidad",
  "no_data_avilable": "No hay datos disponibles",
  "no_data_avilable_to_load": "No hay datos disponibles para cargar.",
  "t_and_c": "T&C aceptados con éxito",
  "no_title_available": "No hay título disponible",
  "no_date_available": "No hay fecha disponible",
  "spin_bonus": "Bono de Giro",
  "check_out_this_link": "Consulta este enlace:",
  "fail_to_open_link": "No se pudo abrir el enlace",
  "no_url_provide": "No se proporcionó URL",
  "text_copy": "¡Texto copiado!",
  "collect_your_reward": "Recoge tus recompensas",
  "code": "Código:",
  "share": "Compartir",
  "collect": "Recoger",
  "select_language": "Seleccionar idioma",
  "give_five_star": "Dar 5 estrellas",
  "share_app": "Compartir aplicación",
  "more_apps": "Más aplicaciones",
  "rate_us": "CALIFÍCANOS",
  "feed_bake": "Escribe tu opinión aquí...",
  "submit": "Enviar",
  "online": "En línea",
  "check_internet_connection": "Verifica la conexión a Internet",
  "Error during fetch:": "Error durante la carga:",
  "offline": "¡Estás sin conexión!",
  "check_internet": "Verificar Internet",
  "retry": "Reintentar",
  "somethinf_went_wrong": "¡Algo salió mal!",
  "tap_again_to_exit": "Toca nuevamente para salir",
  "failed_to_open_link": "No se pudo abrir el enlace",
  "no_url_rovide": "No se proporcionó URL"
}
